Metadata-Version: 2.4
Name: open-aea
Version: 2.0.8
Summary: Open Autonomous Economic Agent framework (without vendor lock-in)
Home-page: https://github.com/valory-xyz/open-aea.git
Author: Valory AG
License: Apache-2.0
Project-URL: Bug Reports, https://github.com/valory-xyz/open-aea/issues
Project-URL: Source, https://github.com/valory-xyz/open-aea
Keywords: aea open-aea autonomous-economic-agents agent-framework multi-agent-systems multi-agent cryptocurrency cryptocurrencies dezentralized dezentralized-network
Classifier: Environment :: Console
Classifier: Environment :: Web Environment
Classifier: Development Status :: 5 - Production/Stable
Classifier: Intended Audience :: Developers
Classifier: License :: OSI Approved :: Apache Software License
Classifier: Natural Language :: English
Classifier: Operating System :: MacOS
Classifier: Operating System :: Microsoft
Classifier: Operating System :: Unix
Classifier: Programming Language :: Python :: 3.10
Classifier: Programming Language :: Python :: 3.11
Classifier: Topic :: Communications
Classifier: Topic :: Internet
Classifier: Topic :: Scientific/Engineering
Classifier: Topic :: Software Development
Classifier: Topic :: System
Requires-Python: >=3.10
License-File: LICENSE
License-File: AUTHORS.md
Requires-Dist: semver<3.0.0,>=2.9.1
Requires-Dist: base58<3.0.0,>=1.0.3
Requires-Dist: jsonschema<4.4.0,>=4.3.0
Requires-Dist: packaging<24.0,>=23.1
Requires-Dist: protobuf<4.25.0,>=4.21.6
Requires-Dist: pymultihash==0.8.2
Requires-Dist: pyyaml<7,>=6.0.1
Requires-Dist: requests<3,>=2.28.1
Requires-Dist: python-dotenv<1.0.1,>=0.14.0
Requires-Dist: ecdsa<0.17.0,>=0.15
Requires-Dist: morphys>=1.0
Requires-Dist: py-multibase>=1.0.0
Requires-Dist: py-multicodec>=0.2.0
Provides-Extra: cli
Requires-Dist: click<8.3.0,>=8.1.0; extra == "cli"
Requires-Dist: pyyaml<9,>=6.0.1; extra == "cli"
Requires-Dist: packaging<24.0,>=23.1; extra == "cli"
Requires-Dist: pytest<8.0.0,>=7.0.0; extra == "cli"
Requires-Dist: coverage<8.0.0,>=6.4.4; extra == "cli"
Requires-Dist: jsonschema<4.4.0,>=4.3.0; extra == "cli"
Requires-Dist: semver<3.0.0,>=2.9.1; extra == "cli"
Provides-Extra: test-tools
Requires-Dist: click<8.3.0,>=8.1.0; extra == "test-tools"
Requires-Dist: pyyaml<9,>=6.0.1; extra == "test-tools"
Requires-Dist: packaging<24.0,>=23.1; extra == "test-tools"
Requires-Dist: pytest<8.0.0,>=7.0.0; extra == "test-tools"
Requires-Dist: coverage<8.0.0,>=6.4.4; extra == "test-tools"
Requires-Dist: jsonschema<4.4.0,>=4.3.0; extra == "test-tools"
Requires-Dist: semver<3.0.0,>=2.9.1; extra == "test-tools"
Provides-Extra: all
Requires-Dist: coverage<8.0.0,>=6.4.4; extra == "all"
Requires-Dist: pyyaml<9,>=6.0.1; extra == "all"
Requires-Dist: click<8.3.0,>=8.1.0; extra == "all"
Requires-Dist: semver<3.0.0,>=2.9.1; extra == "all"
Requires-Dist: pytest<8.0.0,>=7.0.0; extra == "all"
Requires-Dist: packaging<24.0,>=23.1; extra == "all"
Requires-Dist: jsonschema<4.4.0,>=4.3.0; extra == "all"
Dynamic: author
Dynamic: classifier
Dynamic: description
Dynamic: description-content-type
Dynamic: home-page
Dynamic: keywords
Dynamic: license
Dynamic: license-file
Dynamic: project-url
Dynamic: provides-extra
Dynamic: requires-dist
Dynamic: requires-python
Dynamic: summary
